gnpp/__init__.py
gnpp/arg.py
gnpp/cli.py
gnpp/gnpp.py
gnpp/template.py
gnpp/assets/Apache License.txt
gnpp/assets/GNU GENERAL PUBLIC LICENSE.txt
gnpp/assets/MIT.txt
gnpp/assets/README.txt
gnpp/assets/setup.txt
gnpp/assets/unlicense.txt
gnpp-0.1.0.dist-info/LICENSE
gnpp-0.1.0.dist-info/METADATA
gnpp-0.1.0.dist-info/WHEEL
gnpp-0.1.0.dist-info/entry_points.txt
gnpp-0.1.0.dist-info/top_level.txt
gnpp-0.1.0.dist-info/RECORD
