Metadata-Version: 2.1
Name: gnpp
Version: 0.1.0
Summary: Simple tool for generate new project python
Home-page: https://gitlab.com/nesstero/gnpp
Author: nestero
Author-email: nestero@mail.com
License: MIT
Platform: UNKNOWN
License-File: LICENSE
